odoo/addons/stock_vertical_lift/README.rst
odoo/addons/stock_vertical_lift/__init__.py
odoo/addons/stock_vertical_lift/__manifest__.py
odoo/addons/stock_vertical_lift/controllers/__init__.py
odoo/addons/stock_vertical_lift/controllers/main.py
odoo/addons/stock_vertical_lift/data/ir_sequence.xml
odoo/addons/stock_vertical_lift/demo/product_demo.xml
odoo/addons/stock_vertical_lift/demo/stock_inventory_demo.xml
odoo/addons/stock_vertical_lift/demo/stock_location_demo.xml
odoo/addons/stock_vertical_lift/demo/stock_picking_demo.xml
odoo/addons/stock_vertical_lift/demo/vertical_lift_shuttle_demo.xml
odoo/addons/stock_vertical_lift/i18n/stock_vertical_lift.pot
odoo/addons/stock_vertical_lift/images/O-BTN.release.svg
odoo/addons/stock_vertical_lift/images/O-BTN.save.svg
odoo/addons/stock_vertical_lift/images/O-BTN.skip.svg
odoo/addons/stock_vertical_lift/models/__init__.py
odoo/addons/stock_vertical_lift/models/stock_inventory.py
odoo/addons/stock_vertical_lift/models/stock_location.py
odoo/addons/stock_vertical_lift/models/stock_move.py
odoo/addons/stock_vertical_lift/models/stock_move_line.py
odoo/addons/stock_vertical_lift/models/stock_quant.py
odoo/addons/stock_vertical_lift/models/vertical_lift_command.py
odoo/addons/stock_vertical_lift/models/vertical_lift_operation_base.py
odoo/addons/stock_vertical_lift/models/vertical_lift_operation_inventory.py
odoo/addons/stock_vertical_lift/models/vertical_lift_operation_pick.py
odoo/addons/stock_vertical_lift/models/vertical_lift_operation_put.py
odoo/addons/stock_vertical_lift/models/vertical_lift_shuttle.py
odoo/addons/stock_vertical_lift/readme/CONFIGURE.rst
odoo/addons/stock_vertical_lift/readme/CONTRIBUTORS.rst
odoo/addons/stock_vertical_lift/readme/DESCRIPTION.rst
odoo/addons/stock_vertical_lift/readme/DEVELOP.rst
odoo/addons/stock_vertical_lift/readme/ROADMAP.rst
odoo/addons/stock_vertical_lift/security/ir.model.access.csv
odoo/addons/stock_vertical_lift/static/description/icon.png
odoo13_addon_stock_vertical_lift-13.0.1.3.1.dist-info/METADATA
odoo13_addon_stock_vertical_lift-13.0.1.3.1.dist-info/WHEEL
odoo13_addon_stock_vertical_lift-13.0.1.3.1.dist-info/top_level.txt
odoo13_addon_stock_vertical_lift-13.0.1.3.1.dist-info/RECORD
