Metadata-Version: 2.1
Name: odoo13-addon-stock-vertical-lift
Version: 13.0.1.3.1
Summary: Provides the core for integration with Vertical Lifts
Home-page: https://github.com/OCA/stock-logistics-warehouse
Author: Camptocamp, Odoo Community Association (OCA)
Author-email: support@odoo-community.org
License: AGPL-3
Platform: UNKNOWN
Classifier: Programming Language :: Python
Classifier: Framework :: Odoo
Classifier: License :: OSI Approved :: GNU Affero General Public License v3
Classifier: Development Status :: 3 - Alpha
Requires-Python: >=3.5
Requires-Dist: odoo13-addon-stock-location-tray
Requires-Dist: odoo13-addon-web-ir-actions-act-view-reload
Requires-Dist: odoo13-addon-web-notify
Requires-Dist: odoo (<13.1dev,>=13.0a)
